base_api/__init__.py
base_api/base.py
base_api/modules/__init__.py
base_api/modules/config.py
base_api/modules/errors.py
base_api/modules/progress_bars.py
eaf_base_api-2.5.1.dist-info/licenses/LICENSE
eaf_base_api-2.5.1.dist-info/METADATA
eaf_base_api-2.5.1.dist-info/WHEEL
eaf_base_api-2.5.1.dist-info/top_level.txt
eaf_base_api-2.5.1.dist-info/RECORD
