Metadata-Version: 2.4
Name: eaf_base_api
Version: 2.5.1
Summary: A base API for EchterAlsFake's Porn APIs
Author-email: Johannes Habel <EchterAlsFake@proton.me>
License: LGPLv3
Project-URL: Homepage, https://github.com/EchterAlsFake/eaf_base_api
Classifier: License :: OSI Approved :: GNU Lesser General Public License v3 (LGPLv3)
Classifier: Programming Language :: Python
Requires-Python: >=3.6
License-File: LICENSE
Requires-Dist: m3u8
Requires-Dist: httpx[brotli,http2,socks]
Provides-Extra: av
Requires-Dist: av; extra == "av"
Provides-Extra: ffmpeg
Requires-Dist: ffmpeg-progress-yield; extra == "ffmpeg"
Provides-Extra: ua
Requires-Dist: fake-useragent; extra == "ua"
Dynamic: license-file
